gist/__init__.py
gist/_version.py
gist/gist.py
cli_gist-0.1.1.dist-info/LICENSE
cli_gist-0.1.1.dist-info/METADATA
cli_gist-0.1.1.dist-info/WHEEL
cli_gist-0.1.1.dist-info/entry_points.txt
cli_gist-0.1.1.dist-info/top_level.txt
cli_gist-0.1.1.dist-info/RECORD
