Metadata-Version: 2.2
Name: cli_gist
Version: 0.1.1
Summary: Command line to upload and update your gist files.
Author: Fred C. (W6BSD)
License: BSD 3-Clause License
Project-URL: Documentation, https://github.com/0x9900/gist/
Project-URL: Source, https://github.com/0x9900/gist
Project-URL: Tracker, https://github.com/0x9900/gist/issues
Classifier: Intended Audience :: End Users/Desktop
Classifier: License :: OSI Approved :: BSD License
Classifier: Operating System :: OS Independent
Classifier: Development Status :: 2 - Pre-Alpha
Classifier: Environment :: Console
Classifier: Operating System :: Unix
Classifier: Operating System :: POSIX
Classifier: Programming Language :: Python
Classifier: Programming Language :: Python :: 3.10
Classifier: Programming Language :: Python :: 3.11
Classifier: Programming Language :: Python :: 3.12
Requires-Python: >=3.10
License-File: LICENSE
Provides-Extra: dev
Requires-Dist: flake8; extra == "dev"
Requires-Dist: isort; extra == "dev"
Requires-Dist: mypy; extra == "dev"
Requires-Dist: pre-commit; extra == "dev"
Requires-Dist: pylint; extra == "dev"
